{
    "ProjectA": {
      "iamUserName": "Watermelon",
      "inboundFolderPath": "Watermelon/",
      "lambdaCodePath": "scripts/lambda-handler.py",
      "rawBucketFolderPath": "Watermelon/"
    },
        "ProjectB": {
      "iamUserName": "Demo",
      "inboundFolderPath": "Demo/",
      "lambdaCodePath": "scripts/lambda-handler.py",
      "rawBucketFolderPath": "Demo/"
    },
    "ProjectC": {
      "iamUserName": "Demo2",
      "inboundFolderPath": "Demo2/",
      "lambdaCodePath": "scripts/lambda-handler.py",
      "rawBucketFolderPath": "Demo2/"
    }
}
  
